{"singlePage": [], "startSite": "", "filingNum": "", "onePageListNum": 15, "commentLabelColor": "#006b75", "yearColorList": ["#bc4c00", "#0969da", "#1f883d", "#A333D0"], "i18n": "CN", "themeMode": "manual", "dayTheme": "light", "nightTheme": "dark", "urlMode": "pinyin", "script": "", "style": "", "head": "", "indexScript": "", "indexStyle": "", "bottomText": "", "showPostSource": 1, "iconList": {}, "UTC": 8, "rssSplit": "sentence", "exlink": {}, "needComment": 1, "allHead": "", "title": "Shawn's Share", "subTitle": "Code changes the world", "avatarUrl": "https://resource.baigongyi.com/images/20240222/f492765a-965d-4c56-bced-3063b1eda245.jpeg", "GMEEK_VERSION": "last", "postListJson": {}, "singeListJson": {}, "labelColorDict": {"bug": "#d73a4a", "documentation": "#0075ca", "duplicate": "#cfd3d7", "enhancement": "#a2eeef", "good first issue": "#7057ff", "help wanted": "#008672", "invalid": "#e4e669", "question": "#d876e3", "wontfix": "#ffffff"}, "displayTitle": "Shawn's Share", "faviconUrl": "https://resource.baigongyi.com/images/20240222/f492765a-965d-4c56-bced-3063b1eda245.jpeg", "ogImage": "https://resource.baigongyi.com/images/20240222/f492765a-965d-4c56-bced-3063b1eda245.jpeg", "primerCSS": "<link href='https://mirrors.sustech.edu.cn/cdnjs/ajax/libs/Primer/21.0.7/primer.css' rel='stylesheet' />", "homeUrl": "https://ArchitectShawn.github.io/WritingCode", "prevUrl": "disabled", "nextUrl": "disabled"}